openweather.py
setup.py
openweather.egg-info/PKG-INFO
openweather.egg-info/SOURCES.txt
openweather.egg-info/dependency_links.txt
openweather.egg-info/entry_points.txt
openweather.egg-info/requires.txt
openweather.egg-info/top_level.txt