Metadata-Version: 1.0
Name: openweather
Version: 0.7
Summary: OpenWeatherMap.org API wrapper
Home-page: http://github.com/marians/openweather
Author: Marian Steinbach
Author-email: marian@sendung.de
License: UNKNOWN
Platform: UNKNOWN
